{"skeleton": {"hash": "O/99jOFET+VbnuEh4WJWOrxNuhA", "spine": "3.2.01", "width": 653.9999389648438, "height": 5036.8779296875, "images": null}, "bones": [{"name": "root", "parent": null, "rotation": 0.0, "x": 0.0, "y": 0.0, "scaleX": 1.0, "scaleY": 1.0, "shearX": 0.0, "shearY": 0.0, "length": 0.0, "inheritRotation": true, "inheritScale": true, "transform": "normal"}, {"name": "bip", "parent": "root", "rotation": 0.0, "x": 18.97182273864746, "y": 450.8475341796875, "scaleX": 1.0, "scaleY": 1.0, "shearX": 0.0, "shearY": 0.0, "length": 0.0, "inheritRotation": true, "inheritScale": true, "transform": "normal"}, {"name": "pelvis", "parent": "bip", "rotation": 0.0, "x": 20.0, "y": 0.0, "scaleX": 1.0, "scaleY": 1.0, "shearX": 0.0, "shearY": 0.0, "length": 0.0, "inheritRotation": true, "inheritScale": true, "transform": "normal"}, {"name": "doll1_body", "parent": "pelvis", "rotation": 79.3354263305664, "x": 4.694858551025391, "y": 26.04656982421875, "scaleX": 1.0, "scaleY": 1.0, "shearX": 0.0, "shearY": 0.0, "length": 159.84088134765625, "inheritRotation": true, "inheritScale": true, "transform": "normal"}, {"name": "doll1_head", "parent": "doll1_body", "rotation": -23.978818893432617, "x": 154.45135498046875, "y": 1.060943603515625, "scaleX": 1.0, "scaleY": 1.0, "shearX": 0.0, "shearY": 0.0, "length": 297.5985107421875, "inheritRotation": true, "inheritScale": true, "transform": "normal"}, {"name": "bone", "parent": "doll1_head", "rotation": -9.649321556091309, "x": 305.1767578125, "y": 2.85821533203125, "scaleX": 1.0, "scaleY": 1.0, "shearX": 0.0, "shearY": 0.0, "length": 104.70790100097656, "inheritRotation": true, "inheritScale": true, "transform": "normal"}, {"name": "doll1_r_arm", "parent": "doll1_body", "rotation": 146.4086151123047, "x": 110.748291015625, "y": 75.94522857666016, "scaleX": 1.0, "scaleY": 1.0, "shearX": 0.0, "shearY": 0.0, "length": 264.853515625, "inheritRotation": true, "inheritScale": true, "transform": "normal"}, {"name": "bone2", "parent": "doll1_r_arm", "rotation": -0.35163554549217224, "x": 117.15731811523438, "y": -11.9833984375, "scaleX": 1.0, "scaleY": 1.0, "shearX": 0.0, "shearY": 0.0, "length": 106.75473022460938, "inheritRotation": true, "inheritScale": true, "transform": "normal"}, {"name": "doll1_skirt1", "parent": "pelvis", "rotation": -130.49220275878906, "x": -54.675743103027344, "y": 33.276580810546875, "scaleX": 1.0, "scaleY": 1.0, "shearX": 0.0, "shearY": 0.0, "length": 234.3607940673828, "inheritRotation": true, "inheritScale": true, "transform": "normal"}, {"name": "bone3", "parent": "doll1_skirt1", "rotation": 21.812040328979492, "x": 233.8871307373047, "y": -2.84197998046875, "scaleX": 1.0, "scaleY": 1.0, "shearX": 0.0, "shearY": 0.0, "length": 280.64398193359375, "inheritRotation": true, "inheritScale": true, "transform": "normal"}, {"name": "doll1_l_arm", "parent": "doll1_body", "rotation": -147.9322509765625, "x": 92.90106201171875, "y": -26.405410766601562, "scaleX": 1.0, "scaleY": 1.0, "shearX": 0.0, "shearY": 0.0, "length": 259.908447265625, "inheritRotation": true, "inheritScale": true, "transform": "normal"}, {"name": "bone4", "parent": "doll1_l_arm", "rotation": 1.4177930355072021, "x": 143.9759521484375, "y": -10.098541259765625, "scaleX": 1.0, "scaleY": 1.0, "shearX": 0.0, "shearY": 0.0, "length": 73.29902648925781, "inheritRotation": true, "inheritScale": true, "transform": "normal"}, {"name": "doll1_ribbon", "parent": "doll1_body", "rotation": 0.0, "x": 62.0694580078125, "y": -38.287994384765625, "scaleX": 1.0, "scaleY": 1.0, "shearX": 0.0, "shearY": 0.0, "length": 0.0, "inheritRotation": true, "inheritScale": true, "transform": "normal"}, {"name": "doll1_ribbon_l", "parent": "doll1_ribbon", "rotation": -164.8382568359375, "x": -21.88360595703125, "y": -4.833207130432129, "scaleX": 1.0, "scaleY": 1.0, "shearX": 0.0, "shearY": 0.0, "length": 62.49237823486328, "inheritRotation": true, "inheritScale": true, "transform": "normal"}, {"name": "doll1_ribbon_r", "parent": "doll1_ribbon", "rotation": 154.57830810546875, "x": -16.86724853515625, "y": 11.85522747039795, "scaleX": 1.0, "scaleY": 1.0, "shearX": 0.0, "shearY": 0.0, "length": 73.7960433959961, "inheritRotation": true, "inheritScale": true, "transform": "normal"}, {"name": "doll1_skirt2", "parent": "pelvis", "rotation": -57.85059356689453, "x": 25.265857696533203, "y": 24.591064453125, "scaleX": 1.0, "scaleY": 1.0, "shearX": 0.0, "shearY": 0.0, "length": 196.5060577392578, "inheritRotation": true, "inheritScale": true, "transform": "normal"}, {"name": "doll1_skirt3", "parent": "pelvis", "rotation": -95.1944351196289, "x": -2.30303955078125, "y": -18.034271240234375, "scaleX": 1.0, "scaleY": 1.0, "shearX": 0.0, "shearY": 0.0, "length": 232.6232147216797, "inheritRotation": true, "inheritScale": true, "transform": "normal"}, {"name": "doll1_skirt2_1", "parent": "doll1_skirt2", "rotation": -8.68310546875, "x": 194.496337890625, "y": -0.029632568359375, "scaleX": 1.0, "scaleY": 1.0, "shearX": 0.0, "shearY": 0.0, "length": 193.82620239257812, "inheritRotation": true, "inheritScale": true, "transform": "normal"}, {"name": "doll1_skirt3_1", "parent": "doll1_skirt3", "rotation": -0.033762212842702866, "x": 228.94183349609375, "y": 0.0, "scaleX": 1.0, "scaleY": 1.0, "shearX": 0.0, "shearY": 0.0, "length": 194.96807861328125, "inheritRotation": true, "inheritScale": true, "transform": "normal"}, {"name": "line1", "parent": "root", "rotation": 0.0, "x": 0.0, "y": 5036.8779296875, "scaleX": 1.0, "scaleY": 1.0, "shearX": 0.0, "shearY": 0.0, "length": 0.0, "inheritRotation": true, "inheritScale": true, "transform": "normal"}, {"name": "line1_1", "parent": "line1", "rotation": -89.64263916015625, "x": -5.464111328125, "y": -36.1513671875, "scaleX": 1.0, "scaleY": 1.0, "shearX": 0.0, "shearY": 0.0, "length": 1918.288818359375, "inheritRotation": true, "inheritScale": true, "transform": "normal"}, {"name": "line1_2", "parent": "line1_1", "rotation": 0.19219207763671875, "x": 1917.984375, "y": 0.0, "scaleX": 1.0, "scaleY": 1.0, "shearX": 0.0, "shearY": 0.0, "length": 1610.0, "inheritRotation": true, "inheritScale": true, "transform": "normal"}, {"name": "ik_line1", "parent": "line1_2", "rotation": -0.192840576171875, "x": 1610.0, "y": 0.0, "scaleX": 1.0, "scaleY": 1.0, "shearX": 0.0, "shearY": 0.0, "length": 0.0, "inheritRotation": true, "inheritScale": true, "transform": "normal"}, {"name": "line2", "parent": "root", "rotation": 0.0, "x": -194.73291015625, "y": 4995.5703125, "scaleX": 1.0, "scaleY": 1.0, "shearX": 0.0, "shearY": 0.0, "length": 0.0, "inheritRotation": true, "inheritScale": true, "transform": "normal"}, {"name": "line1_4", "parent": "line2", "rotation": -89.64263916015625, "x": -5.464111328125, "y": -36.1513671875, "scaleX": 1.0, "scaleY": 1.0, "shearX": 0.0, "shearY": 0.0, "length": 1918.288818359375, "inheritRotation": true, "inheritScale": true, "transform": "normal"}, {"name": "line1_5", "parent": "line1_4", "rotation": 0.19219207763671875, "x": 1917.984375, "y": 0.0, "scaleX": 1.0, "scaleY": 1.0, "shearX": 0.0, "shearY": 0.0, "length": 1610.0, "inheritRotation": true, "inheritScale": true, "transform": "normal"}, {"name": "ik_line2", "parent": "line1_5", "rotation": -0.192840576171875, "x": 1610.0, "y": 0.0, "scaleX": 1.0, "scaleY": 1.0, "shearX": 0.0, "shearY": 0.0, "length": 0.0, "inheritRotation": true, "inheritScale": true, "transform": "normal"}, {"name": "line3", "parent": "root", "rotation": 0.0, "x": 135.15618896484375, "y": 4944.25, "scaleX": 1.0, "scaleY": 1.0, "shearX": 0.0, "shearY": 0.0, "length": 0.0, "inheritRotation": true, "inheritScale": true, "transform": "normal"}, {"name": "line1_7", "parent": "line3", "rotation": -89.64263916015625, "x": -5.464111328125, "y": -36.1513671875, "scaleX": 1.0, "scaleY": 1.0, "shearX": 0.0, "shearY": 0.0, "length": 1918.288818359375, "inheritRotation": true, "inheritScale": true, "transform": "normal"}, {"name": "line1_8", "parent": "line1_7", "rotation": 0.19219207763671875, "x": 1917.984375, "y": 0.0, "scaleX": 1.0, "scaleY": 1.0, "shearX": 0.0, "shearY": 0.0, "length": 1610.0, "inheritRotation": true, "inheritScale": true, "transform": "normal"}, {"name": "ik_line3", "parent": "line1_8", "rotation": -0.192840576171875, "x": 1610.0, "y": 0.0, "scaleX": 1.0, "scaleY": 1.0, "shearX": 0.0, "shearY": 0.0, "length": 0.0, "inheritRotation": true, "inheritScale": true, "transform": "normal"}, {"name": "line1_3", "parent": "pelvis", "rotation": 90.15565490722656, "x": -14.358448028564453, "y": 21.896148681640625, "scaleX": 1.0, "scaleY": 1.0, "shearX": 0.0, "shearY": 0.0, "length": 1000.0, "inheritRotation": true, "inheritScale": true, "transform": "normal"}, {"name": "line1_6", "parent": "doll1_r_arm", "rotation": -135.58840942382812, "x": 231.98825073242188, "y": 3.139617919921875, "scaleX": 1.0, "scaleY": 1.0, "shearX": 0.0, "shearY": 0.0, "length": 1000.0, "inheritRotation": true, "inheritScale": true, "transform": "normal"}, {"name": "line1_9", "parent": "doll1_l_arm", "rotation": 158.75247192382812, "x": 197.18038940429688, "y": 1.079071044921875, "scaleX": 1.0, "scaleY": 1.0, "shearX": 0.0, "shearY": 0.0, "length": 1000.0, "inheritRotation": true, "inheritScale": true, "transform": "normal"}], "ik": [{"name": "ik_line1", "bones": ["line1_3"], "target": "ik_line1", "mix": 1.0, "bendPositive": true, "order": 0}, {"name": "ik_line2", "bones": ["line1_6"], "target": "ik_line2", "mix": 1.0, "bendPositive": true, "order": 1}, {"name": "ik_line3", "bones": ["line1_9"], "target": "ik_line3", "mix": 1.0, "bendPositive": true, "order": 2}], "transform": [], "slots": [{"name": "line1", "bone": "line1", "color": "#ffffffff", "attachment": "line", "blend": "normal"}, {"name": "line2", "bone": "line2", "color": "#ffffffff", "attachment": "line", "blend": "normal"}, {"name": "line3", "bone": "line3", "color": "#ffffffff", "attachment": "line", "blend": "normal"}, {"name": "doll1_l_arm_dwn", "bone": "doll1_l_arm", "color": "#ffffffff", "attachment": "doll1_l_arm_dwn", "blend": "normal"}, {"name": "doll1_l_arm_up", "bone": "doll1_l_arm", "color": "#ffffffff", "attachment": "doll1_l_arm_up", "blend": "normal"}, {"name": "doll1_skirt3", "bone": "doll1_skirt3", "color": "#ffffffff", "attachment": "doll1_skirt3", "blend": "normal"}, {"name": "doll1_skirt2", "bone": "doll1_skirt2", "color": "#ffffffff", "attachment": "doll1_skirt2", "blend": "normal"}, {"name": "doll1_skirt1", "bone": "doll1_skirt1", "color": "#ffffffff", "attachment": "doll1_skirt1", "blend": "normal"}, {"name": "doll1_body", "bone": "doll1_body", "color": "#ffffffff", "attachment": "doll1_body", "blend": "normal"}, {"name": "doll1_head", "bone": "doll1_head", "color": "#ffffffff", "attachment": "doll1_head", "blend": "normal"}, {"name": "doll1_ribbon", "bone": "doll1_ribbon", "color": "#ffffffff", "attachment": "doll1_ribbon", "blend": "normal"}, {"name": "doll1_r_arm_dwn", "bone": "doll1_r_arm", "color": "#ffffffff", "attachment": "doll1_r_arm_dwn", "blend": "normal"}, {"name": "doll1_r_arm_up", "bone": "doll1_r_arm", "color": "#ffffffff", "attachment": "doll1_r_arm_up", "blend": "normal"}], "skins": {"default": {"line1": {"line": {"name": "line", "type": "mesh", "color": "#ffffffff", "uvs": [0.5315080881118774, 0.07959315925836563, 0.5532256960868835, 0.1548720896244049, 0.5825434923171997, 0.24475637078285217, 0.6157740354537964, 0.34663644433021545, 0.6184775233268738, 0.37834566831588745, 0.6218726634979248, 0.4181675910949707, 0.6260185837745667, 0.4667953550815582, 0.6299353837966919, 0.5127358436584473, 0.6670098304748535, 0.5476168990135193, 0.7044918537139893, 0.5828813910484314, 0.7414408326148987, 0.6176443696022034, 0.7802737355232239, 0.6541798114776611, 0.8228527307510376, 0.7321061491966248, 0.8475682735443115, 0.7773394584655762, 0.872790515422821, 0.8235002160072327, 0.9010955095291138, 0.8627726435661316, 0.9282849431037903, 0.9004972577095032, 0.9614864587783813, 0.9465634226799011, 1.0, 1.0, 0.26598456501960754, 0.9999899864196777, 0.2588590383529663, 0.945673942565918, 0.2528739273548126, 0.9000511765480042, 0.24798160791397095, 0.8627582788467407, 0.24285535514354706, 0.8236821889877319, 0.21118874847888947, 0.7777325510978699, 0.1800166517496109, 0.732500433921814, 0.1272093653678894, 0.6558747291564941, 0.09227389842271805, 0.6167687177658081, 0.061948634684085846, 0.5828232765197754, 0.03047914057970047, 0.5475969910621643, 1.180847357318271e-05, 0.5134924650192261, 8.522045391146094e-06, 0.46678978204727173, 5.1003180487896316e-06, 0.4181644022464752, 2.3087006866262527e-06, 0.37849336862564087, 0.0, 0.3456849455833435, 0.0, 0.2447546422481537, 0.0, 0.15414702892303467, 0.0, 0.07959216833114624, 0.0, 0.0, 0.5085487365722656, 1.0065741662401706e-05], "triangles": [19, 17, 18, 19, 20, 17, 20, 16, 17, 20, 21, 16, 21, 15, 16, 21, 22, 15, 22, 14, 15, 22, 23, 14, 23, 13, 14, 23, 24, 13, 24, 12, 13, 24, 25, 12, 25, 11, 12, 25, 26, 11, 26, 10, 11, 26, 27, 10, 27, 9, 10, 27, 28, 9, 28, 8, 9, 28, 29, 8, 29, 7, 8, 29, 30, 7, 30, 6, 7, 30, 31, 6, 31, 5, 6, 31, 32, 5, 32, 4, 5, 32, 33, 4, 33, 3, 4, 33, 34, 3, 34, 2, 3, 34, 35, 2, 35, 1, 2, 35, 36, 1, 36, 0, 1, 36, 37, 0, 37, 39, 0, 37, 38, 39], "vertices": [2.0, 20.0, 328.8500061035156, 23.010000228881836, 0.9964500069618225, 21.0, -1589.0400390625, 28.34000015258789, 0.003539999946951866, 2.0, 20.0, 673.9299926757812, 22.200000762939453, 0.986519992351532, 21.0, -1243.9599609375, 26.3799991607666, 0.0134699996560812, 2.0, 20.0, 1085.9599609375, 21.450000762939453, 0.9603700041770935, 21.0, -831.9299926757812, 24.239999771118164, 0.03962000086903572, 3.0, 20.0, 1552.989990234375, 20.600000381469727, 0.9044700264930725, 21.0, -364.9200134277344, 21.81999969482422, 0.09551999717950821, 31.0, 2975.139892578125, -8.15999984741211, 0.0, 3.0, 20.0, 1698.3399658203125, 19.860000610351562, 0.806879997253418, 21.0, -219.57000732421875, 20.600000381469727, 0.1931000053882599, 31.0, 2829.780029296875, -7.940000057220459, 9.999999747378752e-06, 3.0, 20.0, 1880.8800048828125, 18.93000030517578, 0.6662399768829346, 21.0, -37.029998779296875, 19.059999465942383, 0.3336400091648102, 31.0, 2647.239990234375, -7.659999847412109, 9.999999747378752e-05, 3.0, 20.0, 2103.7900390625, 17.799999237060547, 0.4978500008583069, 21.0, 185.86000061035156, 17.18000030517578, 0.5013999938964844, 31.0, 2424.330078125, -7.320000171661377, 0.0007300000288523734, 3.0, 20.0, 2314.3701171875, 16.729999542236328, 0.32986000180244446, 21.0, 396.44000244140625, 15.399999618530273, 0.6665499806404114, 31.0, 2213.739990234375, -7.0, 0.0035699999425560236, 3.0, 20.0, 2474.280029296875, 18.030000686645508, 0.19019000232219696, 21.0, 556.3499755859375, 16.15999984741211, 0.7965599894523621, 31.0, 2053.840087890625, -8.869999885559082, 0.01322999969124794, 3.0, 20.0, 2635.93994140625, 19.350000381469727, 0.09371999651193619, 21.0, 718.02001953125, 16.940000534057617, 0.8672599792480469, 31.0, 1892.1800537109375, -10.760000228881836, 0.039009999483823776, 3.0, 20.0, 2795.31005859375, 20.639999389648438, 0.03872000053524971, 21.0, 877.3900146484375, 17.700000762939453, 0.8669800162315369, 31.0, 1732.8199462890625, -12.630000114440918, 0.09429000318050385, 3.0, 20.0, 2962.800048828125, 22.010000228881836, 0.013120000250637531, 21.0, 1044.8800048828125, 18.5, 0.7957599759101868, 31.0, 1565.3399658203125, -14.59000015258789, 0.19111000001430511, 3.0, 20.0, 3320.02001953125, 22.420000076293945, 0.003539999946951866, 21.0, 1402.1099853515625, 17.709999084472656, 0.6653599739074707, 31.0, 1208.1199951171875, -16.270000457763672, 0.3310900032520294, 3.0, 20.0, 3527.3798828125, 22.65999984741211, 0.0007300000288523734, 21.0, 1609.4599609375, 17.260000228881836, 0.5000600218772888, 31.0, 1000.760009765625, -17.25, 0.4991999864578247, 3.0, 20.0, 3738.97998046875, 22.899999618530273, 9.999999747378752e-05, 21.0, 1821.0699462890625, 16.790000915527344, 0.3324100077152252, 31.0, 789.1599731445312, -18.25, 0.6674699783325195, 3.0, 20.0, 3919.02001953125, 23.530000686645508, 9.999999747378752e-06, 21.0, 2001.0999755859375, 16.81999969482422, 0.19207000732421875, 31.0, 609.1300048828125, -19.530000686645508, 0.8079100251197815, 3.0, 20.0, 4091.949951171875, 24.139999389648438, 0.0, 21.0, 2174.0400390625, 16.850000381469727, 0.094200000166893, 31.0, 436.20001220703125, -20.75, 0.9057899713516235, 2.0, 21.0, 2385.219970703125, 16.8799991607666, 0.03571999818086624, 31.0, 225.02000427246094, -22.239999771118164, 0.9642699956893921, 1.0, 31.0, -19.93000030517578, -23.979999542236328, 1.0, 1.0, 31.0, -19.760000228881836, 21.520000457763672, 1.0, 2.0, 21.0, 2380.719970703125, -26.6299991607666, 0.03571999818086624, 31.0, 229.22000122070312, 21.299999237060547, 0.9642699956893921, 3.0, 20.0, 4089.64990234375, -17.709999084472656, 0.0, 21.0, 2171.590087890625, -25.0, 0.094200000166893, 31.0, 438.3500061035156, 21.110000610351562, 0.9057899713516235, 3.0, 20.0, 3918.699951171875, -16.950000762939453, 9.999999747378752e-06, 21.0, 2000.6500244140625, -23.65999984741211, 0.19207000732421875, 31.0, 609.2999877929688, 20.959999084472656, 0.8079100251197815, 3.0, 20.0, 3739.580078125, -16.149999618530273, 9.999999747378752e-05, 21.0, 1821.530029296875, -22.260000228881836, 0.3324100077152252, 31.0, 788.4299926757812, 20.799999237060547, 0.6674699783325195, 3.0, 20.0, 3528.929931640625, -16.799999237060547, 0.0007300000288523734, 21.0, 1610.8800048828125, -22.200000762939453, 0.5000600218772888, 31.0, 999.0700073242188, 22.200000762939453, 0.4991999864578247, 3.0, 20.0, 3321.580078125, -17.440000534057617, 0.003539999946951866, 21.0, 1403.530029296875, -22.149999618530273, 0.6653599739074707, 31.0, 1206.4100341796875, 23.579999923706055, 0.3310900032520294, 3.0, 20.0, 2970.320068359375, -18.520000457763672, 0.013120000250637531, 21.0, 1052.260009765625, -22.049999237060547, 0.7957599759101868, 31.0, 1557.6700439453125, 25.90999984741211, 0.19111000001430511, 3.0, 20.0, 2791.0400390625, -19.56999969482422, 0.03872000053524971, 21.0, 872.989990234375, -22.5, 0.8669800162315369, 31.0, 1736.93994140625, 27.600000381469727, 0.09429000318050385, 3.0, 20.0, 2635.429931640625, -20.479999542236328, 0.09371999651193619, 21.0, 717.3699951171875, -22.889999389648438, 0.8672599792480469, 31.0, 1892.550048828125, 29.059999465942383, 0.039009999483823776, 3.0, 20.0, 2473.93994140625, -21.420000076293945, 0.19019000232219696, 21.0, 555.8800048828125, -23.290000915527344, 0.7965599894523621, 31.0, 2054.030029296875, 30.579999923706055, 0.01322999969124794, 3.0, 20.0, 2317.60009765625, -22.34000015258789, 0.32986000180244446, 21.0, 399.5400085449219, -23.68000030517578, 0.6665499806404114, 31.0, 2210.3701171875, 32.04999923706055, 0.0035699999425560236, 3.0, 20.0, 2103.52001953125, -21.0, 0.49786001443862915, 21.0, 185.4600067138672, -21.6299991607666, 0.5013899803161621, 31.0, 2424.4599609375, 31.479999542236328, 0.0007300000288523734, 3.0, 20.0, 1880.6199951171875, -19.610000610351562, 0.6662399768829346, 21.0, -37.41999816894531, -19.489999771118164, 0.3336400091648102, 31.0, 2647.35009765625, 30.889999389648438, 9.999999747378752e-05, 3.0, 20.0, 1698.780029296875, -18.479999542236328, 0.806879997253418, 21.0, -219.25999450683594, -17.739999771118164, 0.1931000053882599, 31.0, 2829.2099609375, 30.399999618530273, 9.999999747378752e-06, 3.0, 20.0, 1548.3900146484375, -17.540000915527344, 0.9044700264930725, 21.0, -369.6499938964844, -16.299999237060547, 0.09551999717950821, 31.0, 2979.60009765625, 30.0, 0.0, 2.0, 20.0, 1085.72998046875, -14.65999984741211, 0.9603700041770935, 21.0, -832.2899780273438, -11.859999656677246, 0.03962000086903572, 2.0, 20.0, 670.3900146484375, -12.0600004196167, 0.986519992351532, 21.0, -1247.6199951171875, -7.880000114440918, 0.0134699996560812, 2.0, 20.0, 328.6400146484375, -9.930000305175781, 0.9964500069618225, 21.0, -1589.3599853515625, -4.599999904632568, 0.003539999946951866, 1.0, 20.0, -36.189998626708984, -7.659999847412109, 1.0, 1.0, 20.0, -35.95000076293945, 23.860000610351562, 1.0], "hull": 40}}, "line2": {"line": {"name": "line", "type": "mesh", "color": "#ffffffff", "uvs": [0.5315080881118774, 0.07959315925836563, 0.5532256960868835, 0.1548720896244049, 0.5825434923171997, 0.24475637078285217, 0.6157740354537964, 0.34663644433021545, 0.6184775233268738, 0.37834566831588745, 0.6218726634979248, 0.4181675910949707, 0.6260185837745667, 0.4667953550815582, 0.6299353837966919, 0.5127358436584473, 0.6670098304748535, 0.5476168990135193, 0.7044918537139893, 0.5828813910484314, 0.7414408326148987, 0.6176443696022034, 0.7802737355232239, 0.6541798114776611, 0.8228527307510376, 0.7321061491966248, 0.8475682735443115, 0.7773394584655762, 0.872790515422821, 0.8235002160072327, 0.9010955095291138, 0.8627726435661316, 0.9282849431037903, 0.9004972577095032, 0.9614864587783813, 0.9465634226799011, 1.0, 1.0, 0.26598456501960754, 0.9999899864196777, 0.2588590383529663, 0.945673942565918, 0.2528739273548126, 0.9000511765480042, 0.24798160791397095, 0.8627582788467407, 0.24285535514354706, 0.8236821889877319, 0.21118874847888947, 0.7777325510978699, 0.1800166517496109, 0.732500433921814, 0.1272093653678894, 0.6558747291564941, 0.09227389842271805, 0.6167687177658081, 0.061948634684085846, 0.5828232765197754, 0.03047914057970047, 0.5475969910621643, 1.180847357318271e-05, 0.5134924650192261, 8.522045391146094e-06, 0.46678978204727173, 5.1003180487896316e-06, 0.4181644022464752, 2.3087006866262527e-06, 0.37849336862564087, 0.0, 0.3456849455833435, 0.0, 0.2447546422481537, 0.0, 0.15414702892303467, 0.0, 0.07959216833114624, 0.0, 0.0, 0.5085487365722656, 1.0065741662401706e-05], "triangles": [19, 17, 18, 19, 20, 17, 20, 16, 17, 20, 21, 16, 21, 15, 16, 21, 22, 15, 22, 14, 15, 22, 23, 14, 23, 13, 14, 23, 24, 13, 24, 12, 13, 24, 25, 12, 25, 11, 12, 25, 26, 11, 26, 10, 11, 26, 27, 10, 27, 9, 10, 27, 28, 9, 28, 8, 9, 28, 29, 8, 29, 7, 8, 29, 30, 7, 30, 6, 7, 30, 31, 6, 31, 5, 6, 31, 32, 5, 32, 4, 5, 32, 33, 4, 33, 3, 4, 33, 34, 3, 34, 2, 3, 34, 35, 2, 35, 1, 2, 35, 36, 1, 36, 0, 1, 36, 37, 0, 37, 39, 0, 37, 38, 39], "vertices": [2.0, 24.0, 328.8500061035156, 23.010000228881836, 0.9964500069618225, 25.0, -1589.0400390625, 28.34000015258789, 0.003539999946951866, 2.0, 24.0, 673.9299926757812, 22.200000762939453, 0.986519992351532, 25.0, -1243.9599609375, 26.3799991607666, 0.0134699996560812, 2.0, 24.0, 1085.9599609375, 21.450000762939453, 0.9603700041770935, 25.0, -831.9299926757812, 24.239999771118164, 0.03962000086903572, 3.0, 24.0, 1552.989990234375, 20.600000381469727, 0.9044700264930725, 25.0, -364.9200134277344, 21.81999969482422, 0.09551999717950821, 32.0, 2975.139892578125, -8.15999984741211, 0.0, 3.0, 24.0, 1698.3399658203125, 19.860000610351562, 0.806879997253418, 25.0, -219.57000732421875, 20.600000381469727, 0.1931000053882599, 32.0, 2829.780029296875, -7.940000057220459, 9.999999747378752e-06, 3.0, 24.0, 1880.8800048828125, 18.93000030517578, 0.6662399768829346, 25.0, -37.029998779296875, 19.059999465942383, 0.3336400091648102, 32.0, 2647.239990234375, -7.659999847412109, 9.999999747378752e-05, 3.0, 24.0, 2103.7900390625, 17.799999237060547, 0.4978500008583069, 25.0, 185.86000061035156, 17.18000030517578, 0.5013999938964844, 32.0, 2424.330078125, -7.320000171661377, 0.0007300000288523734, 3.0, 24.0, 2314.3701171875, 16.729999542236328, 0.32986000180244446, 25.0, 396.44000244140625, 15.399999618530273, 0.6665499806404114, 32.0, 2213.739990234375, -7.0, 0.0035699999425560236, 3.0, 24.0, 2474.280029296875, 18.030000686645508, 0.19019000232219696, 25.0, 556.3499755859375, 16.15999984741211, 0.7965599894523621, 32.0, 2053.840087890625, -8.869999885559082, 0.01322999969124794, 3.0, 24.0, 2635.93994140625, 19.350000381469727, 0.09371999651193619, 25.0, 718.02001953125, 16.940000534057617, 0.8672599792480469, 32.0, 1892.1800537109375, -10.760000228881836, 0.039009999483823776, 3.0, 24.0, 2795.31005859375, 20.639999389648438, 0.03872000053524971, 25.0, 877.3900146484375, 17.700000762939453, 0.8669800162315369, 32.0, 1732.8199462890625, -12.630000114440918, 0.09429000318050385, 3.0, 24.0, 2962.800048828125, 22.010000228881836, 0.013120000250637531, 25.0, 1044.8800048828125, 18.5, 0.7957599759101868, 32.0, 1565.3399658203125, -14.59000015258789, 0.19111000001430511, 3.0, 24.0, 3320.02001953125, 22.420000076293945, 0.003539999946951866, 25.0, 1402.1099853515625, 17.709999084472656, 0.6653599739074707, 32.0, 1208.1199951171875, -16.270000457763672, 0.3310900032520294, 3.0, 24.0, 3527.3798828125, 22.65999984741211, 0.0007300000288523734, 25.0, 1609.4599609375, 17.260000228881836, 0.5000600218772888, 32.0, 1000.760009765625, -17.25, 0.4991999864578247, 3.0, 24.0, 3738.97998046875, 22.899999618530273, 9.999999747378752e-05, 25.0, 1821.0699462890625, 16.790000915527344, 0.3324100077152252, 32.0, 789.1599731445312, -18.25, 0.6674699783325195, 3.0, 24.0, 3919.02001953125, 23.530000686645508, 9.999999747378752e-06, 25.0, 2001.0999755859375, 16.81999969482422, 0.19207000732421875, 32.0, 609.1300048828125, -19.530000686645508, 0.8079100251197815, 3.0, 24.0, 4091.949951171875, 24.139999389648438, 0.0, 25.0, 2174.0400390625, 16.850000381469727, 0.094200000166893, 32.0, 436.20001220703125, -20.75, 0.9057899713516235, 2.0, 25.0, 2385.219970703125, 16.8799991607666, 0.03571999818086624, 32.0, 225.02000427246094, -22.239999771118164, 0.9642699956893921, 1.0, 32.0, -19.93000030517578, -23.979999542236328, 1.0, 1.0, 32.0, -19.760000228881836, 21.520000457763672, 1.0, 2.0, 25.0, 2380.719970703125, -26.6299991607666, 0.03571999818086624, 32.0, 229.22000122070312, 21.299999237060547, 0.9642699956893921, 3.0, 24.0, 4089.64990234375, -17.709999084472656, 0.0, 25.0, 2171.590087890625, -25.0, 0.094200000166893, 32.0, 438.3500061035156, 21.110000610351562, 0.9057899713516235, 3.0, 24.0, 3918.699951171875, -16.950000762939453, 9.999999747378752e-06, 25.0, 2000.6500244140625, -23.65999984741211, 0.19207000732421875, 32.0, 609.2999877929688, 20.959999084472656, 0.8079100251197815, 3.0, 24.0, 3739.580078125, -16.149999618530273, 9.999999747378752e-05, 25.0, 1821.530029296875, -22.260000228881836, 0.3324100077152252, 32.0, 788.4299926757812, 20.799999237060547, 0.6674699783325195, 3.0, 24.0, 3528.929931640625, -16.799999237060547, 0.0007300000288523734, 25.0, 1610.8800048828125, -22.200000762939453, 0.5000600218772888, 32.0, 999.0700073242188, 22.200000762939453, 0.4991999864578247, 3.0, 24.0, 3321.580078125, -17.440000534057617, 0.003539999946951866, 25.0, 1403.530029296875, -22.149999618530273, 0.6653599739074707, 32.0, 1206.4100341796875, 23.579999923706055, 0.3310900032520294, 3.0, 24.0, 2970.320068359375, -18.520000457763672, 0.013120000250637531, 25.0, 1052.260009765625, -22.049999237060547, 0.7957599759101868, 32.0, 1557.6700439453125, 25.90999984741211, 0.19111000001430511, 3.0, 24.0, 2791.0400390625, -19.56999969482422, 0.03872000053524971, 25.0, 872.989990234375, -22.5, 0.8669800162315369, 32.0, 1736.93994140625, 27.600000381469727, 0.09429000318050385, 3.0, 24.0, 2635.429931640625, -20.479999542236328, 0.09371999651193619, 25.0, 717.3699951171875, -22.889999389648438, 0.8672599792480469, 32.0, 1892.550048828125, 29.059999465942383, 0.039009999483823776, 3.0, 24.0, 2473.93994140625, -21.420000076293945, 0.19019000232219696, 25.0, 555.8800048828125, -23.290000915527344, 0.7965599894523621, 32.0, 2054.030029296875, 30.579999923706055, 0.01322999969124794, 3.0, 24.0, 2317.60009765625, -22.34000015258789, 0.32986000180244446, 25.0, 399.5400085449219, -23.68000030517578, 0.6665499806404114, 32.0, 2210.3701171875, 32.04999923706055, 0.0035699999425560236, 3.0, 24.0, 2103.52001953125, -21.0, 0.49786001443862915, 25.0, 185.4600067138672, -21.6299991607666, 0.5013899803161621, 32.0, 2424.4599609375, 31.479999542236328, 0.0007300000288523734, 3.0, 24.0, 1880.6199951171875, -19.610000610351562, 0.6662399768829346, 25.0, -37.41999816894531, -19.489999771118164, 0.3336400091648102, 32.0, 2647.35009765625, 30.889999389648438, 9.999999747378752e-05, 3.0, 24.0, 1698.780029296875, -18.479999542236328, 0.806879997253418, 25.0, -219.25999450683594, -17.739999771118164, 0.1931000053882599, 32.0, 2829.2099609375, 30.399999618530273, 9.999999747378752e-06, 3.0, 24.0, 1548.3900146484375, -17.540000915527344, 0.9044700264930725, 25.0, -369.6499938964844, -16.299999237060547, 0.09551999717950821, 32.0, 2979.60009765625, 30.0, 0.0, 2.0, 24.0, 1085.72998046875, -14.65999984741211, 0.9603700041770935, 25.0, -832.2899780273438, -11.859999656677246, 0.03962000086903572, 2.0, 24.0, 670.3900146484375, -12.0600004196167, 0.986519992351532, 25.0, -1247.6199951171875, -7.880000114440918, 0.0134699996560812, 2.0, 24.0, 328.6400146484375, -9.930000305175781, 0.9964500069618225, 25.0, -1589.3599853515625, -4.599999904632568, 0.003539999946951866, 1.0, 24.0, -36.189998626708984, -7.659999847412109, 1.0, 1.0, 24.0, -35.95000076293945, 23.860000610351562, 1.0], "hull": 40}}, "line3": {"line": {"name": "line", "type": "mesh", "color": "#ffffffff", "uvs": [0.5315080881118774, 0.07959315925836563, 0.5532256960868835, 0.1548720896244049, 0.5825434923171997, 0.24475637078285217, 0.6157740354537964, 0.34663644433021545, 0.6184775233268738, 0.37834566831588745, 0.6218726634979248, 0.4181675910949707, 0.6260185837745667, 0.4667953550815582, 0.6299353837966919, 0.5127358436584473, 0.6670098304748535, 0.5476168990135193, 0.7044918537139893, 0.5828813910484314, 0.7414408326148987, 0.6176443696022034, 0.7802737355232239, 0.6541798114776611, 0.8228527307510376, 0.7321061491966248, 0.8475682735443115, 0.7773394584655762, 0.872790515422821, 0.8235002160072327, 0.9010955095291138, 0.8627726435661316, 0.9282849431037903, 0.9004972577095032, 0.9614864587783813, 0.9465634226799011, 1.0, 1.0, 0.26598456501960754, 0.9999899864196777, 0.2588590383529663, 0.945673942565918, 0.2528739273548126, 0.9000511765480042, 0.24798160791397095, 0.8627582788467407, 0.24285535514354706, 0.8236821889877319, 0.21118874847888947, 0.7777325510978699, 0.1800166517496109, 0.732500433921814, 0.1272093653678894, 0.6558747291564941, 0.09227389842271805, 0.6167687177658081, 0.061948634684085846, 0.5828232765197754, 0.03047914057970047, 0.5475969910621643, 1.180847357318271e-05, 0.5134924650192261, 8.522045391146094e-06, 0.46678978204727173, 5.1003180487896316e-06, 0.4181644022464752, 2.3087006866262527e-06, 0.37849336862564087, 0.0, 0.3456849455833435, 0.0, 0.2447546422481537, 0.0, 0.15414702892303467, 0.0, 0.07959216833114624, 0.0, 0.0, 0.5085487365722656, 1.0065741662401706e-05], "triangles": [19, 17, 18, 19, 20, 17, 20, 16, 17, 20, 21, 16, 21, 15, 16, 21, 22, 15, 22, 14, 15, 22, 23, 14, 23, 13, 14, 23, 24, 13, 24, 12, 13, 24, 25, 12, 25, 11, 12, 25, 26, 11, 26, 10, 11, 26, 27, 10, 27, 9, 10, 27, 28, 9, 28, 8, 9, 28, 29, 8, 29, 7, 8, 29, 30, 7, 30, 6, 7, 30, 31, 6, 31, 5, 6, 31, 32, 5, 32, 4, 5, 32, 33, 4, 33, 3, 4, 33, 34, 3, 34, 2, 3, 34, 35, 2, 35, 1, 2, 35, 36, 1, 36, 0, 1, 36, 37, 0, 37, 39, 0, 37, 38, 39], "vertices": [2.0, 28.0, 328.8500061035156, 23.010000228881836, 0.9964500069618225, 29.0, -1589.0400390625, 28.34000015258789, 0.003539999946951866, 2.0, 28.0, 673.9299926757812, 22.200000762939453, 0.986519992351532, 29.0, -1243.9599609375, 26.3799991607666, 0.0134699996560812, 2.0, 28.0, 1085.9599609375, 21.450000762939453, 0.9603700041770935, 29.0, -831.9299926757812, 24.239999771118164, 0.03962000086903572, 3.0, 28.0, 1552.989990234375, 20.600000381469727, 0.9044700264930725, 29.0, -364.9200134277344, 21.81999969482422, 0.09551999717950821, 33.0, 2975.139892578125, -8.15999984741211, 0.0, 3.0, 28.0, 1698.3399658203125, 19.860000610351562, 0.806879997253418, 29.0, -219.57000732421875, 20.600000381469727, 0.1931000053882599, 33.0, 2829.780029296875, -7.940000057220459, 9.999999747378752e-06, 3.0, 28.0, 1880.8800048828125, 18.93000030517578, 0.6662399768829346, 29.0, -37.029998779296875, 19.059999465942383, 0.3336400091648102, 33.0, 2647.239990234375, -7.659999847412109, 9.999999747378752e-05, 3.0, 28.0, 2103.7900390625, 17.799999237060547, 0.4978500008583069, 29.0, 185.86000061035156, 17.18000030517578, 0.5013999938964844, 33.0, 2424.330078125, -7.320000171661377, 0.0007300000288523734, 3.0, 28.0, 2314.3701171875, 16.729999542236328, 0.32986000180244446, 29.0, 396.44000244140625, 15.399999618530273, 0.6665499806404114, 33.0, 2213.739990234375, -7.0, 0.0035699999425560236, 3.0, 28.0, 2474.280029296875, 18.030000686645508, 0.19019000232219696, 29.0, 556.3499755859375, 16.15999984741211, 0.7965599894523621, 33.0, 2053.840087890625, -8.869999885559082, 0.01322999969124794, 3.0, 28.0, 2635.93994140625, 19.350000381469727, 0.09371999651193619, 29.0, 718.02001953125, 16.940000534057617, 0.8672599792480469, 33.0, 1892.1800537109375, -10.760000228881836, 0.039009999483823776, 3.0, 28.0, 2795.31005859375, 20.639999389648438, 0.03872000053524971, 29.0, 877.3900146484375, 17.700000762939453, 0.8669800162315369, 33.0, 1732.8199462890625, -12.630000114440918, 0.09429000318050385, 3.0, 28.0, 2962.800048828125, 22.010000228881836, 0.013120000250637531, 29.0, 1044.8800048828125, 18.5, 0.7957599759101868, 33.0, 1565.3399658203125, -14.59000015258789, 0.19111000001430511, 3.0, 28.0, 3320.02001953125, 22.420000076293945, 0.003539999946951866, 29.0, 1402.1099853515625, 17.709999084472656, 0.6653599739074707, 33.0, 1208.1199951171875, -16.270000457763672, 0.3310900032520294, 3.0, 28.0, 3527.3798828125, 22.65999984741211, 0.0007300000288523734, 29.0, 1609.4599609375, 17.260000228881836, 0.5000600218772888, 33.0, 1000.760009765625, -17.25, 0.4991999864578247, 3.0, 28.0, 3738.97998046875, 22.899999618530273, 9.999999747378752e-05, 29.0, 1821.0699462890625, 16.790000915527344, 0.3324100077152252, 33.0, 789.1599731445312, -18.25, 0.6674699783325195, 3.0, 28.0, 3919.02001953125, 23.530000686645508, 9.999999747378752e-06, 29.0, 2001.0999755859375, 16.81999969482422, 0.19207000732421875, 33.0, 609.1300048828125, -19.530000686645508, 0.8079100251197815, 3.0, 28.0, 4091.949951171875, 24.139999389648438, 0.0, 29.0, 2174.0400390625, 16.850000381469727, 0.094200000166893, 33.0, 436.20001220703125, -20.75, 0.9057899713516235, 2.0, 29.0, 2385.219970703125, 16.8799991607666, 0.03571999818086624, 33.0, 225.02000427246094, -22.239999771118164, 0.9642699956893921, 1.0, 33.0, -19.93000030517578, -23.979999542236328, 1.0, 1.0, 33.0, -19.760000228881836, 21.520000457763672, 1.0, 2.0, 29.0, 2380.719970703125, -26.6299991607666, 0.03571999818086624, 33.0, 229.22000122070312, 21.299999237060547, 0.9642699956893921, 3.0, 28.0, 4089.64990234375, -17.709999084472656, 0.0, 29.0, 2171.590087890625, -25.0, 0.094200000166893, 33.0, 438.3500061035156, 21.110000610351562, 0.9057899713516235, 3.0, 28.0, 3918.699951171875, -16.950000762939453, 9.999999747378752e-06, 29.0, 2000.6500244140625, -23.65999984741211, 0.19207000732421875, 33.0, 609.2999877929688, 20.959999084472656, 0.8079100251197815, 3.0, 28.0, 3739.580078125, -16.149999618530273, 9.999999747378752e-05, 29.0, 1821.530029296875, -22.260000228881836, 0.3324100077152252, 33.0, 788.4299926757812, 20.799999237060547, 0.6674699783325195, 3.0, 28.0, 3528.929931640625, -16.799999237060547, 0.0007300000288523734, 29.0, 1610.8800048828125, -22.200000762939453, 0.5000600218772888, 33.0, 999.0700073242188, 22.200000762939453, 0.4991999864578247, 3.0, 28.0, 3321.580078125, -17.440000534057617, 0.003539999946951866, 29.0, 1403.530029296875, -22.149999618530273, 0.6653599739074707, 33.0, 1206.4100341796875, 23.579999923706055, 0.3310900032520294, 3.0, 28.0, 2970.320068359375, -18.520000457763672, 0.013120000250637531, 29.0, 1052.260009765625, -22.049999237060547, 0.7957599759101868, 33.0, 1557.6700439453125, 25.90999984741211, 0.19111000001430511, 3.0, 28.0, 2791.0400390625, -19.56999969482422, 0.03872000053524971, 29.0, 872.989990234375, -22.5, 0.8669800162315369, 33.0, 1736.93994140625, 27.600000381469727, 0.09429000318050385, 3.0, 28.0, 2635.429931640625, -20.479999542236328, 0.09371999651193619, 29.0, 717.3699951171875, -22.889999389648438, 0.8672599792480469, 33.0, 1892.550048828125, 29.059999465942383, 0.039009999483823776, 3.0, 28.0, 2473.93994140625, -21.420000076293945, 0.19019000232219696, 29.0, 555.8800048828125, -23.290000915527344, 0.7965599894523621, 33.0, 2054.030029296875, 30.579999923706055, 0.01322999969124794, 3.0, 28.0, 2317.60009765625, -22.34000015258789, 0.32986000180244446, 29.0, 399.5400085449219, -23.68000030517578, 0.6665499806404114, 33.0, 2210.3701171875, 32.04999923706055, 0.0035699999425560236, 3.0, 28.0, 2103.52001953125, -21.0, 0.49786001443862915, 29.0, 185.4600067138672, -21.6299991607666, 0.5013899803161621, 33.0, 2424.4599609375, 31.479999542236328, 0.0007300000288523734, 3.0, 28.0, 1880.6199951171875, -19.610000610351562, 0.6662399768829346, 29.0, -37.41999816894531, -19.489999771118164, 0.3336400091648102, 33.0, 2647.35009765625, 30.889999389648438, 9.999999747378752e-05, 3.0, 28.0, 1698.780029296875, -18.479999542236328, 0.806879997253418, 29.0, -219.25999450683594, -17.739999771118164, 0.1931000053882599, 33.0, 2829.2099609375, 30.399999618530273, 9.999999747378752e-06, 3.0, 28.0, 1548.3900146484375, -17.540000915527344, 0.9044700264930725, 29.0, -369.6499938964844, -16.299999237060547, 0.09551999717950821, 33.0, 2979.60009765625, 30.0, 0.0, 2.0, 28.0, 1085.72998046875, -14.65999984741211, 0.9603700041770935, 29.0, -832.2899780273438, -11.859999656677246, 0.03962000086903572, 2.0, 28.0, 670.3900146484375, -12.0600004196167, 0.986519992351532, 29.0, -1247.6199951171875, -7.880000114440918, 0.0134699996560812, 2.0, 28.0, 328.6400146484375, -9.930000305175781, 0.9964500069618225, 29.0, -1589.3599853515625, -4.599999904632568, 0.003539999946951866, 1.0, 28.0, -36.189998626708984, -7.659999847412109, 1.0, 1.0, 28.0, -35.95000076293945, 23.860000610351562, 1.0], "hull": 40}}, "doll1_l_arm_dwn": {"doll1_l_arm_dwn": {"name": "doll1_l_arm_dwn", "type": "region", "rotation": 68.5968246459961, "x": 187.71200561523438, "y": -8.8592529296875, "scaleX": 1.0, "scaleY": 1.0, "width": 91.0, "height": 144.0, "color": "#ffffffff"}}, "doll1_l_arm_up": {"doll1_l_arm_up": {"name": "doll1_l_arm_up", "type": "mesh", "color": "#ffffffff", "uvs": [0.9999995231628418, 0.7673415541648865, 0.9860020875930786, 0.8984287977218628, 0.6024797558784485, 1.0, 0.07126599550247192, 1.0, 0.0, 1.0, 0.0, 0.4613429307937622, 0.0, 0.0, 0.4579712748527527, 5.433708429336548e-05, 1.0, 0.0, 0.13378383219242096, 0.7256003618240356, 0.7282128930091858, 0.5399631261825562], "triangles": [0, 2, 10, 1, 2, 0, 3, 4, 9, 3, 9, 2, 4, 5, 9, 5, 6, 7, 10, 7, 8, 5, 7, 10, 9, 5, 10, 0, 10, 8, 2, 9, 10], "vertices": [1.0, 11.0, 55.93000030517578, 73.80999755859375, 1.0, 1.0, 11.0, 83.66000366210938, 59.599998474121094, 1.0, 1.0, 11.0, 80.86000061035156, -9.119999885559082, 1.0, 1.0, 11.0, 46.2400016784668, -91.37999725341797, 1.0, 2.0, 10.0, 188.10000610351562, -111.44999694824219, 0.0004600000102072954, 11.0, 41.599998474121094, -102.41000366210938, 0.999530017375946, 1.0, 10.0, 69.23999786376953, -64.86000061035156, 1.0, 1.0, 10.0, -32.54999923706055, -24.959999084472656, 1.0, 1.0, 10.0, -4.460000038146973, 46.65999984741211, 1.0, 1.0, 10.0, 28.75, 131.44000244140625, 1.0, 1.0, 10.0, 135.75, -66.79000091552734, 1.0, 1.0, 10.0, 131.22999572753906, 42.22999954223633, 1.0], "hull": 9}}, "doll1_skirt3": {"doll1_skirt3": {"name": "doll1_skirt3", "type": "mesh", "color": "#ffffffff", "uvs": [0.9996398687362671, 0.5850191712379456, 1.0, 0.7693634033203125, 1.0, 1.0, 0.6399614810943604, 1.0, 0.31475138664245605, 1.0, 0.0, 1.0, 0.0, 0.7693631649017334, 9.989737918658648e-06, 0.5774276256561279, 0.0, 0.0, 0.3463136851787567, 0.0, 0.6726236939430237, 0.0, 1.0, 0.0, 0.1018037497997284, 0.3071887493133545, 0.8911201357841492, 0.33137473464012146, 0.044478967785835266, 0.44441458582878113, 0.9558826684951782, 0.45395025610923767, 0.3241325616836548, 0.7693632245063782, 0.6352710723876953, 0.769363284111023, 0.3412885069847107, 0.5800194144248962, 0.6307313442230225, 0.5822175741195679, 0.3851168155670166, 0.44797855615615845, 0.600906252861023, 0.4502362906932831], "triangles": [7, 8, 14, 16, 6, 7, 18, 16, 7, 17, 19, 0, 18, 19, 17, 16, 18, 17, 17, 0, 1, 4, 5, 6, 16, 4, 6, 3, 17, 1, 16, 17, 3, 4, 16, 3, 3, 1, 2, 12, 8, 9, 13, 10, 11, 9, 10, 13, 12, 9, 13, 14, 8, 12, 21, 20, 12, 14, 12, 20, 13, 21, 12, 15, 13, 11, 21, 13, 15, 18, 14, 20, 7, 14, 18, 19, 21, 15, 20, 21, 19, 18, 20, 19, 0, 15, 11, 19, 15, 0], "vertices": [2.0, 16.0, 212.9600067138672, 191.99000549316406, 0.5, 18.0, -16.09000015258789, 191.97999572753906, 0.5, 2.0, 16.0, 302.8999938964844, 200.3300018310547, 0.265639990568161, 18.0, 73.83999633789062, 200.3699951171875, 0.7343500256538391, 1.0, 18.0, 186.38999938964844, 210.6699981689453, 1.0, 1.0, 18.0, 200.58999633789062, 55.41999816894531, 1.0, 1.0, 18.0, 213.4199981689453, -84.80000305175781, 1.0, 1.0, 18.0, 225.83999633789062, -220.52000427246094, 1.0, 2.0, 16.0, 342.1099853515625, -230.8800048828125, 0.2624399960041046, 18.0, 113.30000305175781, -230.82000732421875, 0.7375500202178955, 2.0, 16.0, 248.44000244140625, -239.38999938964844, 0.5, 18.0, 19.639999389648438, -239.3800048828125, 0.5, 1.0, 18.0, -262.1099853515625, -265.1700134277344, 1.0, 1.0, 16.0, -46.900001525878906, -115.68000030517578, 1.0, 1.0, 16.0, -59.689998626708984, 25.020000457763672, 1.0, 1.0, 16.0, -72.52999877929688, 166.1999969482422, 1.0, 1.0, 16.0, 112.58000183105469, -207.49000549316406, 1.0, 1.0, 16.0, 93.44000244140625, 133.9499969482422, 1.0, 2.0, 16.0, 181.7899932861328, -226.1199951171875, 0.7601699829101562, 18.0, -47.0099983215332, -226.14999389648438, 0.23982000350952148, 2.0, 16.0, 150.7100067138672, 167.30999755859375, 0.756600022315979, 18.0, -78.31999969482422, 167.25999450683594, 0.24338999390602112, 2.0, 16.0, 329.3999938964844, -91.11000061035156, 0.263480007648468, 18.0, 100.51000213623047, -91.05000305175781, 0.7365099787712097, 2.0, 16.0, 317.20001220703125, 43.04999923706055, 0.26447001099586487, 18.0, 88.2300033569336, 43.099998474121094, 0.7355200052261353, 2.0, 16.0, 236.3300018310547, -92.11000061035156, 0.5, 18.0, 7.440000057220459, -92.11000061035156, 0.5, 2.0, 16.0, 226.0500030517578, 32.790000915527344, 0.5, 18.0, -2.9000000953674316, 32.790000915527344, 0.5, 2.0, 16.0, 170.17999267578125, -79.06999969482422, 0.7588300108909607, 18.0, -58.709999084472656, -79.11000061035156, 0.24116000533103943, 2.0, 16.0, 162.82000732421875, 14.069999694824219, 0.7579900026321411, 18.0, -66.12000274658203, 14.029999732971191, 0.24199999868869781], "hull": 12}}, "doll1_skirt2": {"doll1_skirt2": {"name": "doll1_skirt2", "type": "mesh", "color": "#ffffffff", "uvs": [1.0, 0.7022557854652405, 1.0, 1.0, 0.6363746523857117, 0.9999899864196777, 0.0, 1.0, 0.0, 0.07225579023361206, 0.0, 0.0, 0.22686411440372467, 0.0, 1.0, 0.0, 0.26877501606941223, 0.27049720287323, 0.3777334988117218, 0.5083748698234558, 0.7806848883628845, 0.39820370078086853, 0.5759798288345337, 0.18471308052539825, 0.5082542896270752, 0.7516940236091614, 0.9368337392807007, 0.6149129867553711], "triangles": [12, 9, 10, 13, 7, 0, 12, 10, 13, 3, 12, 2, 2, 12, 13, 2, 13, 0, 2, 0, 1, 4, 5, 6, 11, 6, 7, 8, 6, 11, 4, 6, 8, 10, 11, 7, 9, 8, 11, 9, 11, 10, 13, 10, 7, 3, 4, 8, 3, 8, 9, 3, 9, 12], "vertices": [1.0, 17.0, 142.52999877929688, 42.81999969482422, 1.0, 1.0, 17.0, 257.239990234375, -6.96999979019165, 1.0, 1.0, 17.0, 223.5, -84.68000030517578, 1.0, 1.0, 15.0, 323.75, -243.02999877929688, 1.0, 1.0, 15.0, -6.139999866485596, -35.68000030517578, 1.0, 1.0, 15.0, -31.829999923706055, -19.530000686645508, 1.0, 1.0, 15.0, -3.7100000381469727, 25.209999084472656, 1.0, 1.0, 15.0, 92.13999938964844, 177.72999572753906, 1.0, 2.0, 15.0, 97.66999816894531, -26.969999313354492, 0.75, 17.0, -91.63999938964844, -41.2400016784668, 0.25, 2.0, 15.0, 195.77000427246094, -58.630001068115234, 0.5, 17.0, 10.100000381469727, -57.7400016784668, 0.5, 2.0, 15.0, 206.5500030517578, 45.470001220703125, 0.5, 17.0, 5.050000190734863, 46.79999923706055, 0.5, 2.0, 15.0, 105.25, 52.79999923706055, 0.75, 17.0, -96.19000244140625, 38.75, 0.25, 2.0, 15.0, 298.4700012207031, -87.2699966430664, 0.25, 17.0, 115.95999908447266, -70.54000091552734, 0.75, 2.0, 15.0, 302.9700012207031, 27.84000015258789, 0.25, 17.0, 103.0199966430664, 43.93000030517578, 0.75], "hull": 8}}, "doll1_skirt1": {"doll1_skirt1": {"name": "doll1_skirt1", "type": "mesh", "color": "#ffffffff", "uvs": [1.0, 1.0, 0.13314515352249146, 1.0, 0.0, 1.0, 8.806586265563965e-06, 0.6050553917884827, 0.0, 0.0, 0.8155863285064697, 0.0, 1.0, 0.0, 0.08006643503904343, 0.2988044321537018, 0.4137042760848999, 0.14000777900218964, 0.781464159488678, 0.34417492151260376, 0.5784196257591248, 0.5424583554267883, 0.44024357199668884, 0.7978795766830444], "triangles": [3, 7, 10, 11, 3, 10, 1, 11, 0, 1, 2, 3, 11, 1, 3, 8, 4, 5, 7, 4, 8, 9, 8, 5, 10, 8, 9, 7, 8, 10, 3, 4, 7, 9, 5, 6, 0, 9, 6, 10, 9, 0, 11, 10, 0], "vertices": [1.0, 8.0, 322.54998779296875, 324.6600036621094, 1.0, 1.0, 9.0, 284.25, 33.790000915527344, 1.0, 1.0, 9.0, 296.57000732421875, -2.6500000953674316, 1.0, 2.0, 8.0, 365.1400146484375, -18.979999542236328, 0.25, 9.0, 115.86000061035156, -63.75, 0.75, 1.0, 8.0, 142.88999938964844, -208.74000549316406, 1.0, 1.0, 8.0, -10.149999618530273, -29.489999771118164, 1.0, 1.0, 8.0, -44.7599983215332, 11.029999732971191, 1.0, 2.0, 8.0, 237.6199951171875, -97.43000030517578, 0.5, 9.0, -31.670000076293945, -89.20999908447266, 0.5, 2.0, 8.0, 116.68000030517578, -73.91000366210938, 0.75, 9.0, -135.2100067138672, -22.43000030517578, 0.25, 2.0, 8.0, 122.66999816894531, 70.94000244140625, 0.75, 9.0, -75.83000183105469, 109.83000183105469, 0.25, 2.0, 8.0, 233.60000610351562, 88.51000213623047, 0.5, 9.0, 33.68000030517578, 84.91000366210938, 0.5, 2.0, 8.0, 353.3500061035156, 138.25, 0.25, 9.0, 163.33999633789062, 86.5999984741211, 0.75], "hull": 7}}, "doll1_body": {"doll1_body": {"name": "doll1_body", "type": "region", "rotation": -79.3354263305664, "x": 84.60614013671875, "y": 13.299034118652344, "scaleX": 1.0, "scaleY": 1.0, "width": 197.0, "height": 227.0, "color": "#ffffffff"}}, "doll1_head": {"doll1_head": {"name": "doll1_head", "type": "mesh", "color": "#ffffffff", "uvs": [1.0, 0.13764643669128418, 1.0, 0.4233412742614746, 1.0, 1.0, 0.8743057250976562, 1.0, 0.0, 1.0, 0.0, 0.4833919405937195, 0.0, 0.30142077803611755, 0.0, 0.0, 0.3737372159957886, 0.0, 0.7618975043296814, 0.0, 1.0, 0.0, 0.4387233853340149, 0.2923222780227661, 0.6530018448829651, 0.3014205992221832, 0.8339090347290039, 0.4797523617744446, 0.8487290740013123, 0.6706114411354065], "triangles": [1, 13, 0, 12, 9, 0, 9, 10, 0, 11, 8, 9, 12, 11, 9, 2, 14, 1, 3, 4, 14, 14, 4, 11, 14, 11, 12, 12, 13, 14, 2, 3, 14, 4, 5, 11, 14, 13, 1, 5, 6, 11, 13, 12, 0, 6, 8, 11, 6, 7, 8], "vertices": [2.0, 4.0, 435.95001220703125, -82.30999755859375, 0.004720000084489584, 5.0, 143.1999969482422, -62.04999923706055, 0.9952700138092041, 2.0, 4.0, 338.1700134277344, -149.8699951171875, 0.4084300100803375, 5.0, 58.130001068115234, -145.0399932861328, 0.5915600061416626, 1.0, 4.0, 140.80999755859375, -286.239990234375, 1.0, 1.0, 4.0, 110.01000213623047, -241.6699981689453, 1.0, 1.0, 4.0, -104.19000244140625, 68.33000183105469, 1.0, 1.0, 4.0, 72.61000061035156, 190.5, 1.0, 2.0, 4.0, 134.88999938964844, 233.52999877929688, 0.9700000286102295, 5.0, -206.5399932861328, 198.8699951171875, 0.029999999329447746, 2.0, 4.0, 238.0500030517578, 304.80999755859375, 0.9594500064849854, 5.0, -116.77999877929688, 286.42999267578125, 0.040539998561143875, 2.0, 4.0, 329.6199951171875, 172.2899932861328, 0.800000011920929, 5.0, -4.300000190734863, 171.1300048828125, 0.20000000298023224, 1.0, 5.0, 112.5199966430664, 51.38999938964844, 1.0, 1.0, 5.0, 184.17999267578125, -22.059999465942383, 1.0, 2.0, 4.0, 245.49000549316406, 80.12000274658203, 0.8100000023841858, 5.0, -71.77999877929688, 66.16999816894531, 0.1899999976158142, 1.0, 4.0, 294.8800048828125, 1.9900000095367432, 1.0, 1.0, 4.0, 278.1700134277344, -104.31999969482422, 1.0, 1.0, 4.0, 216.47999572753906, -154.7100067138672, 1.0], "hull": 11}}, "doll1_ribbon": {"doll1_ribbon": {"name": "doll1_ribbon", "type": "mesh", "color": "#ffffffff", "uvs": [1.0, 0.3922964930534363, 1.0, 1.0, 0.8563908338546753, 0.9999901056289673, 0.6362546682357788, 0.9999893307685852, 0.0, 1.0, 0.0, 0.8170602321624756, 0.0, 0.0, 0.550750732421875, 0.0, 1.0, 0.0, 0.5943571329116821, 0.4385320246219635, 0.7517759203910828, 0.4825614392757416, 0.4793657958507538, 0.3539142310619354, 0.4109557867050171, 0.1901494711637497, 0.6461762189865112, 0.4801290035247803, 0.3683018982410431, 0.7791070342063904], "triangles": [1, 2, 10, 3, 10, 2, 12, 5, 6, 14, 5, 11, 4, 5, 14, 4, 14, 3, 3, 13, 10, 1, 10, 0, 14, 9, 13, 12, 6, 7, 5, 12, 11, 14, 11, 9, 10, 13, 9, 9, 11, 7, 7, 10, 9, 10, 7, 8, 11, 12, 7, 10, 8, 0, 3, 14, 13], "vertices": [1.0, 12.0, -6.079999923706055, -38.77000045776367, 1.0, 1.0, 13.0, 76.0199966430664, 30.399999618530273, 1.0, 1.0, 13.0, 74.69999694824219, 13.649999618530273, 1.0, 1.0, 13.0, 72.68000030517578, -12.010000228881836, 1.0, 1.0, 14.0, 104.2300033569336, -4.769999980926514, 1.0, 1.0, 14.0, 84.12000274658203, -19.420000076293945, 1.0, 2.0, 12.0, 24.690000534057617, 86.08000183105469, 0.15623000264167786, 14.0, -5.670000076293945, -84.87000274658203, 0.8437600135803223, 1.0, 12.0, 36.61000061035156, 22.75, 1.0, 1.0, 12.0, 46.34000015258789, -28.889999389648438, 1.0, 1.0, 12.0, -21.049999237060547, 6.699999809265137, 1.0, 1.0, 12.0, -23.520000457763672, -12.5, 1.0, 1.0, 12.0, -12.229999542236328, 22.049999237060547, 1.0, 1.0, 12.0, 8.170000076293945, 34.040000915527344, 1.0, 1.0, 12.0, -25.479999542236328, -0.28999999165534973, 1.0, 1.0, 14.0, 54.56999969482422, 12.350000381469727, 1.0], "hull": 9}}, "doll1_r_arm_dwn": {"doll1_r_arm_dwn": {"name": "doll1_r_arm_dwn", "type": "region", "rotation": 134.2559356689453, "x": 186.81973266601562, "y": 7.091400146484375, "scaleX": 1.0, "scaleY": 1.0, "width": 133.0, "height": 119.0, "color": "#ffffffff"}}, "doll1_r_arm_up": {"doll1_r_arm_up": {"name": "doll1_r_arm_up", "type": "mesh", "color": "#ffffffff", "uvs": [1.0, 0.26761847734451294, 1.0, 1.0, 0.6174235343933105, 1.0, 0.0, 1.0, 0.0, 0.278714120388031, 0.0, 0.0, 0.7771409153938293, 0.0, 1.0, 0.0, 0.4483107328414917, 0.26576972007751465, 0.7414395809173584, 0.5653402209281921, 0.2789027690887451, 0.2706611454486847, 0.706080973148346, 0.6892675161361694, 0.06123046949505806, 0.6282135844230652, 0.33556899428367615, 0.8981970548629761], "triangles": [4, 5, 10, 2, 11, 1, 12, 4, 10, 12, 10, 13, 3, 4, 12, 3, 12, 13, 2, 13, 11, 3, 13, 2, 13, 10, 11, 8, 5, 6, 6, 7, 0, 10, 5, 8, 0, 9, 8, 0, 8, 6, 11, 8, 9, 10, 8, 11, 9, 0, 1, 11, 9, 1], "vertices": [1.0, 6.0, 5.75, 52.93000030517578, 1.0, 1.0, 6.0, 137.94000244140625, 181.72999572753906, 1.0, 1.0, 7.0, 86.22000122070312, 126.29000091552734, 1.0, 1.0, 6.0, 311.010009765625, 4.099999904632568, 1.0, 1.0, 7.0, 64.3499984741211, -110.36000061035156, 1.0, 1.0, 6.0, 130.52000427246094, -171.75, 1.0, 1.0, 6.0, -3.9700000286102295, -33.709999084472656, 1.0, 1.0, 6.0, -42.540000915527344, 5.860000133514404, 1.0, 1.0, 6.0, 100.9000015258789, -45.380001068115234, 1.0, 1.0, 6.0, 104.23999786376953, 59.36000061035156, 1.0, 2.0, 6.0, 131.10000610351562, -74.61000061035156, 0.49000000953674316, 7.0, 14.329999923706055, -62.540000915527344, 0.5099999904632568, 2.0, 6.0, 132.72999572753906, 74.87000274658203, 0.49000000953674316, 7.0, 15.029999732971191, 86.94999694824219, 0.5099999904632568, 1.0, 7.0, 116.38999938964844, -37.70000076293945, 1.0, 1.0, 7.0, 117.05000305175781, 58.5099983215332, 1.0], "hull": 8}}}}, "events": [], "animations": {"Idle1": {"slots": {"doll1_body": {"attachment": [{"time": 0.0, "name": "doll1_body"}, {"time": 2.0, "name": "doll1_body"}]}, "doll1_head": {"attachment": [{"time": 0.0, "name": "doll1_head"}, {"time": 2.0, "name": "doll1_head"}]}, "doll1_l_arm_dwn": {"attachment": [{"time": 0.0, "name": "doll1_l_arm_dwn"}, {"time": 2.0, "name": "doll1_l_arm_dwn"}]}, "doll1_l_arm_up": {"attachment": [{"time": 0.0, "name": "doll1_l_arm_up"}, {"time": 2.0, "name": "doll1_l_arm_up"}]}, "doll1_r_arm_dwn": {"attachment": [{"time": 0.0, "name": "doll1_r_arm_dwn"}, {"time": 2.0, "name": "doll1_r_arm_dwn"}]}, "doll1_r_arm_up": {"attachment": [{"time": 0.0, "name": "doll1_r_arm_up"}, {"time": 2.0, "name": "doll1_r_arm_up"}]}, "doll1_ribbon": {"attachment": [{"time": 0.0, "name": "doll1_ribbon"}, {"time": 2.0, "name": "doll1_ribbon"}]}, "doll1_skirt1": {"attachment": [{"time": 0.0, "name": "doll1_skirt1"}, {"time": 2.0, "name": "doll1_skirt1"}]}, "doll1_skirt2": {"attachment": [{"time": 0.0, "name": "doll1_skirt2"}, {"time": 2.0, "name": "doll1_skirt2"}]}, "doll1_skirt3": {"attachment": [{"time": 0.0, "name": "doll1_skirt3"}, {"time": 2.0, "name": "doll1_skirt3"}]}, "line1": {"attachment": [{"time": 0.0, "name": "line"}, {"time": 2.0, "name": "line"}]}, "line2": {"attachment": [{"time": 0.0, "name": "line"}, {"time": 2.0, "name": "line"}]}, "line3": {"attachment": [{"time": 0.0, "name": "line"}, {"time": 2.0, "name": "line"}]}}, "bones": {"pelvis": {"rotate": [{"time": 0.0, "angle": 0.0, "curve": [0.25, 0.0, 0.75, 1.0]}, {"time": 1.0, "angle": 3.71697998046875, "curve": [0.25, 0.0, 0.75, 1.0]}, {"time": 2.0, "angle": 0.0}], "translate": [{"time": 0.0, "x": 0.0, "y": 0.0, "curve": "stepped"}, {"time": 1.0, "x": 0.0, "y": 0.0, "curve": "stepped"}, {"time": 2.0, "x": 0.0, "y": 0.0}], "scale": [{"time": 0.0, "x": 1.0, "y": 1.0, "curve": "stepped"}, {"time": 1.0, "x": 1.0, "y": 1.0, "curve": "stepped"}, {"time": 2.0, "x": 1.0, "y": 1.0}]}, "root": {"rotate": [{"time": 0.0, "angle": 0.0, "curve": "stepped"}, {"time": 1.0, "angle": 0.0, "curve": "stepped"}, {"time": 2.0, "angle": 0.0}], "translate": [{"time": 0.0, "x": 0.0, "y": 0.0, "curve": "stepped"}, {"time": 1.0, "x": 0.0, "y": 0.0, "curve": "stepped"}, {"time": 2.0, "x": 0.0, "y": 0.0}], "scale": [{"time": 0.0, "x": 1.0, "y": 1.0, "curve": "stepped"}, {"time": 1.0, "x": 1.0, "y": 1.0, "curve": "stepped"}, {"time": 2.0, "x": 1.0, "y": 1.0}]}, "bip": {"rotate": [{"time": 0.0, "angle": 0.0, "curve": "stepped"}, {"time": 1.0, "angle": 0.0, "curve": "stepped"}, {"time": 2.0, "angle": 0.0}], "translate": [{"time": 0.0, "x": -47.327945709228516, "y": 0.0, "curve": [0.25, 0.0, 0.75, 1.0]}, {"time": 1.0, "x": 42.4320068359375, "y": 0.0, "curve": [0.25, 0.0, 0.75, 1.0]}, {"time": 2.0, "x": -47.327945709228516, "y": 0.0}], "scale": [{"time": 0.0, "x": 1.0, "y": 1.0, "curve": "stepped"}, {"time": 1.0, "x": 1.0, "y": 1.0, "curve": "stepped"}, {"time": 2.0, "x": 1.0, "y": 1.0}]}, "doll1_body": {"rotate": [{"time": 0.0, "angle": 0.0, "curve": [0.25, 0.0, 0.75, 1.0]}, {"time": 1.0, "angle": 2.5325469970703125, "curve": [0.25, 0.0, 0.75, 1.0]}, {"time": 2.0, "angle": 0.0}], "translate": [{"time": 0.0, "x": 0.0, "y": 0.0, "curve": "stepped"}, {"time": 1.0, "x": 0.0, "y": 0.0, "curve": "stepped"}, {"time": 2.0, "x": 0.0, "y": 0.0}], "scale": [{"time": 0.0, "x": 1.0, "y": 1.0, "curve": "stepped"}, {"time": 1.0, "x": 1.0, "y": 1.0, "curve": "stepped"}, {"time": 2.0, "x": 1.0, "y": 1.0}]}, "doll1_head": {"rotate": [{"time": 0.0, "angle": -25.991003036499023, "curve": [0.375, 0.5, 0.75, 1.0]}, {"time": 0.5, "angle": -29.00391960144043, "curve": [0.25, 0.0, 0.75, 1.0]}, {"time": 1.5, "angle": -22.978086471557617, "curve": [0.25, 0.0, 0.625, 0.5]}, {"time": 2.0, "angle": -25.991003036499023}], "translate": [{"time": 0.0, "x": 0.0, "y": 0.0, "curve": "stepped"}, {"time": 1.0, "x": 0.0, "y": 0.0, "curve": "stepped"}, {"time": 2.0, "x": 0.0, "y": 0.0}], "scale": [{"time": 0.0, "x": 1.0, "y": 1.0, "curve": "stepped"}, {"time": 1.0, "x": 1.0, "y": 1.0, "curve": "stepped"}, {"time": 2.0, "x": 1.0, "y": 1.0}]}, "doll1_r_arm": {"rotate": [{"time": 0.0, "angle": -25.067535400390625, "curve": [0.25, 0.0, 0.75, 1.0]}, {"time": 1.0, "angle": -39.91295623779297, "curve": [0.25, 0.0, 0.75, 1.0]}, {"time": 2.0, "angle": -25.067535400390625}], "translate": [{"time": 0.0, "x": 0.0, "y": 0.0, "curve": "stepped"}, {"time": 1.0, "x": 0.0, "y": 0.0, "curve": "stepped"}, {"time": 2.0, "x": 0.0, "y": 0.0}], "scale": [{"time": 0.0, "x": 1.0, "y": 1.0, "curve": "stepped"}, {"time": 1.0, "x": 1.0, "y": 1.0, "curve": "stepped"}, {"time": 2.0, "x": 1.0, "y": 1.0}]}, "doll1_l_arm": {"rotate": [{"time": 0.0, "angle": 26.8277587890625, "curve": [0.25, 0.0, 0.75, 1.0]}, {"time": 1.0, "angle": 26.020858764648438, "curve": [0.25, 0.0, 0.75, 1.0]}, {"time": 2.0, "angle": 26.8277587890625}], "translate": [{"time": 0.0, "x": 0.0, "y": 0.0, "curve": "stepped"}, {"time": 1.0, "x": 0.0, "y": 0.0, "curve": "stepped"}, {"time": 2.0, "x": 0.0, "y": 0.0}], "scale": [{"time": 0.0, "x": 1.0, "y": 1.0, "curve": "stepped"}, {"time": 1.0, "x": 1.0, "y": 1.0, "curve": "stepped"}, {"time": 2.0, "x": 1.0, "y": 1.0}]}, "doll1_skirt1": {"rotate": [{"time": 0.0, "angle": 0.6700592041015625, "curve": [0.3292025625705719, 0.3181818127632141, 0.7575430870056152, 1.0]}, {"time": 0.7666666507720947, "angle": 4.028167724609375, "curve": [0.25, 0.0, 0.75, 1.0]}, {"time": 1.7666666507720947, "angle": 0.0, "curve": null}, {"time": 2.0, "angle": 0.6700592041015625}], "translate": [{"time": 0.0, "x": 0.0, "y": 0.0, "curve": "stepped"}, {"time": 1.0, "x": 0.0, "y": 0.0, "curve": "stepped"}, {"time": 2.0, "x": 0.0, "y": 0.0}], "scale": [{"time": 0.0, "x": 1.0, "y": 1.0, "curve": "stepped"}, {"time": 1.0, "x": 1.0, "y": 1.0, "curve": "stepped"}, {"time": 2.0, "x": 1.0, "y": 1.0}]}, "doll1_ribbon": {"rotate": [{"time": 0.0, "angle": 0.0, "curve": "stepped"}, {"time": 1.0, "angle": 0.0, "curve": "stepped"}, {"time": 2.0, "angle": 0.0}], "translate": [{"time": 0.0, "x": 0.0, "y": 0.0, "curve": "stepped"}, {"time": 1.0, "x": 0.0, "y": 0.0, "curve": "stepped"}, {"time": 2.0, "x": 0.0, "y": 0.0}], "scale": [{"time": 0.0, "x": 1.0, "y": 1.0, "curve": "stepped"}, {"time": 1.0, "x": 1.0, "y": 1.0, "curve": "stepped"}, {"time": 2.0, "x": 1.0, "y": 1.0}]}, "doll1_ribbon_r": {"rotate": [{"time": 0.0, "angle": 2.79022216796875, "curve": [0.3513513505458832, 0.4000000059604645, 0.7567566633224487, 1.0]}, {"time": 0.6666666865348816, "angle": -6.66656494140625, "curve": [0.25, 0.0, 0.75, 1.0]}, {"time": 1.6666666269302368, "angle": 6.5373992919921875, "curve": [0.2647058665752411, 0.0, 0.6176470518112183, 0.4285714328289032]}, {"time": 2.0, "angle": 2.79022216796875}], "translate": [{"time": 0.0, "x": 0.0, "y": 0.0, "curve": "stepped"}, {"time": 1.0, "x": 0.0, "y": 0.0, "curve": "stepped"}, {"time": 2.0, "x": 0.0, "y": 0.0}], "scale": [{"time": 0.0, "x": 1.0, "y": 1.0, "curve": "stepped"}, {"time": 1.0, "x": 1.0, "y": 1.0, "curve": "stepped"}, {"time": 2.0, "x": 1.0, "y": 1.0}]}, "doll1_ribbon_l": {"rotate": [{"time": 0.0, "angle": 5.6196746826171875, "curve": [0.30043384432792664, 0.21052633225917816, 0.7559652924537659, 1.0]}, {"time": 0.8666666746139526, "angle": -6.66656494140625, "curve": [0.25, 0.0, 0.75, 1.0]}, {"time": 1.8666666746139526, "angle": 6.5373992919921875, "curve": [0.2972258925437927, 0.0, 0.6340819001197815, 0.3658536672592163]}, {"time": 2.0, "angle": 5.6196746826171875}], "translate": [{"time": 0.0, "x": 0.0, "y": 0.0, "curve": "stepped"}, {"time": 1.0, "x": 0.0, "y": 0.0, "curve": "stepped"}, {"time": 2.0, "x": 0.0, "y": 0.0}], "scale": [{"time": 0.0, "x": 1.0, "y": 1.0, "curve": "stepped"}, {"time": 1.0, "x": 1.0, "y": 1.0, "curve": "stepped"}, {"time": 2.0, "x": 1.0, "y": 1.0}]}, "doll1_skirt2": {"rotate": [{"time": 0.0, "angle": 0.6700592041015625, "curve": [0.3780941665172577, 0.6052632331848145, 0.7215346097946167, 1.0]}, {"time": 0.23333333432674408, "angle": 0.0, "curve": null}, {"time": 1.2333333492279053, "angle": 4.028167724609375, "curve": [0.24245688319206238, 0.0, 0.6707973480224609, 0.6818181276321411]}, {"time": 2.0, "angle": 0.6700592041015625}], "translate": [{"time": 0.0, "x": 0.0, "y": 0.0, "curve": "stepped"}, {"time": 1.0, "x": 0.0, "y": 0.0, "curve": "stepped"}, {"time": 2.0, "x": 0.0, "y": 0.0}], "scale": [{"time": 0.0, "x": 1.0, "y": 1.0, "curve": "stepped"}, {"time": 1.0, "x": 1.0, "y": 1.0, "curve": "stepped"}, {"time": 2.0, "x": 1.0, "y": 1.0}]}, "doll1_skirt3": {"rotate": [{"time": 0.0, "angle": 0.0, "curve": [0.25, 0.0, 0.75, 1.0]}, {"time": 1.0, "angle": 4.028167724609375, "curve": [0.25, 0.0, 0.75, 1.0]}, {"time": 2.0, "angle": 0.0}], "translate": [{"time": 0.0, "x": 0.0, "y": 0.0, "curve": "stepped"}, {"time": 1.0, "x": 0.0, "y": 0.0, "curve": "stepped"}, {"time": 2.0, "x": 0.0, "y": 0.0}], "scale": [{"time": 0.0, "x": 1.0, "y": 1.0, "curve": "stepped"}, {"time": 1.0, "x": 1.0, "y": 1.0, "curve": "stepped"}, {"time": 2.0, "x": 1.0, "y": 1.0}]}, "bone3": {"rotate": [{"time": 0.0, "angle": -1.4053459167480469, "curve": [0.375, 0.5, 0.75, 1.0]}, {"time": 0.5, "angle": -9.559747695922852, "curve": [0.25, 0.0, 0.75, 1.0]}, {"time": 1.5, "angle": 6.749057769775391, "curve": [0.25, 0.0, 0.625, 0.5]}, {"time": 2.0, "angle": -1.4053459167480469}], "translate": [{"time": 0.0, "x": 0.0, "y": 0.0, "curve": "stepped"}, {"time": 1.0, "x": 0.0, "y": 0.0, "curve": "stepped"}, {"time": 2.0, "x": 0.0, "y": 0.0}], "scale": [{"time": 0.0, "x": 1.0, "y": 1.0, "curve": "stepped"}, {"time": 1.0, "x": 1.0, "y": 1.0, "curve": "stepped"}, {"time": 2.0, "x": 1.0, "y": 1.0}]}, "doll1_skirt2_1": {"rotate": [{"time": 0.0, "angle": -1.1216907501220703, "curve": [0.2261904776096344, 0.2881355881690979, 0.75, 1.0]}, {"time": 0.5, "angle": -12.624038696289062, "curve": [0.25, 0.0, 0.75, 1.0]}, {"time": 1.5, "angle": 3.9037017822265625, "curve": [0.25, 0.0, 0.625, 0.5]}, {"time": 2.0, "angle": -1.1216907501220703}], "translate": [{"time": 0.0, "x": 0.0, "y": 0.0, "curve": "stepped"}, {"time": 1.0, "x": 0.0, "y": 0.0, "curve": "stepped"}, {"time": 2.0, "x": 0.0, "y": 0.0}], "scale": [{"time": 0.0, "x": 1.0, "y": 1.0, "curve": "stepped"}, {"time": 1.0, "x": 1.0, "y": 1.0, "curve": "stepped"}, {"time": 2.0, "x": 1.0, "y": 1.0}]}, "doll1_skirt3_1": {"rotate": [{"time": 0.0, "angle": -3.110492706298828, "curve": [0.2261904776096344, 0.2881355881690979, 0.75, 1.0]}, {"time": 0.5, "angle": -12.419759750366211, "curve": [0.25, 0.0, 0.75, 1.0]}, {"time": 1.5, "angle": 9.359903335571289, "curve": [0.25, 0.0, 0.625, 0.5]}, {"time": 2.0, "angle": -3.110492706298828}], "translate": [{"time": 0.0, "x": 0.0, "y": 0.0, "curve": "stepped"}, {"time": 1.0, "x": 0.0, "y": 0.0, "curve": "stepped"}, {"time": 2.0, "x": 0.0, "y": 0.0}], "scale": [{"time": 0.0, "x": 1.0, "y": 1.0, "curve": "stepped"}, {"time": 1.0, "x": 1.0, "y": 1.0, "curve": "stepped"}, {"time": 2.0, "x": 1.0, "y": 1.0}]}, "bone4": {"rotate": [{"time": 0.0, "angle": -5.12891149520874, "curve": [0.36274510622024536, 0.4444444179534912, 0.7549020051956177, 1.0]}, {"time": 0.6000000238418579, "angle": -17.42685317993164, "curve": [0.25, 0.0, 0.75, 1.0]}, {"time": 1.600000023841858, "angle": 3.2350924015045166, "curve": null}, {"time": 2.0, "angle": -5.12891149520874}], "translate": [{"time": 0.0, "x": 0.0, "y": 0.0, "curve": "stepped"}, {"time": 2.0, "x": 0.0, "y": 0.0}], "scale": [{"time": 0.0, "x": 1.0, "y": 1.0, "curve": "stepped"}, {"time": 2.0, "x": 1.0, "y": 1.0}]}, "bone2": {"rotate": [{"time": 0.0, "angle": 12.45391845703125, "curve": [0.3823530077934265, 0.5714285373687744, 0.7352941632270813, 1.0]}, {"time": 0.3333333432674408, "angle": 14.900192260742188, "curve": [0.25, 0.0, 0.75, 1.0]}, {"time": 1.3333333730697632, "angle": 6.280235767364502, "curve": [0.2432432472705841, 0.0, 0.6486486792564392, 0.6000000238418579]}, {"time": 2.0, "angle": 12.45391845703125}], "translate": [{"time": 0.0, "x": 0.0, "y": 0.0, "curve": "stepped"}, {"time": 2.0, "x": 0.0, "y": 0.0}], "scale": [{"time": 0.0, "x": 0.8921033143997192, "y": 1.0, "curve": [0.3513513505458832, 0.4000000059604645, 0.7567566633224487, 1.0]}, {"time": 0.6666666865348816, "x": 1.0, "y": 1.0, "curve": [0.25, 0.0, 0.75, 1.0]}, {"time": 1.6666666269302368, "x": 0.849350094795227, "y": 1.0, "curve": null}, {"time": 2.0, "x": 0.8921033143997192, "y": 1.0}]}, "line1_2": {"rotate": [{"time": 0.0, "angle": 0.0, "curve": "stepped"}, {"time": 2.0, "angle": 0.0}], "translate": [{"time": 0.0, "x": 0.0, "y": 0.0, "curve": "stepped"}, {"time": 2.0, "x": 0.0, "y": 0.0}], "scale": [{"time": 0.0, "x": 1.0, "y": 1.0, "curve": "stepped"}, {"time": 2.0, "x": 1.0, "y": 1.0}]}, "line1_7": {"rotate": [{"time": 0.0, "angle": 0.16149139404296875, "curve": [0.25, 0.0, 0.75, 1.0]}, {"time": 1.0, "angle": 1.4618988037109375, "curve": [0.25, 0.0, 0.75, 1.0]}, {"time": 2.0, "angle": 0.16149139404296875}], "translate": [{"time": 0.0, "x": 0.0, "y": 0.0, "curve": "stepped"}, {"time": 2.0, "x": 0.0, "y": 0.0}], "scale": [{"time": 0.0, "x": 1.0, "y": 1.0, "curve": "stepped"}, {"time": 2.0, "x": 1.0, "y": 1.0}]}, "line1_4": {"rotate": [{"time": 0.0, "angle": -1.1118087768554688, "curve": [0.25, 0.0, 0.75, 1.0]}, {"time": 1.0, "angle": -0.25983428955078125, "curve": [0.25, 0.0, 0.75, 1.0]}, {"time": 2.0, "angle": -1.1118087768554688}], "translate": [{"time": 0.0, "x": 0.0, "y": 0.0, "curve": "stepped"}, {"time": 2.0, "x": 0.0, "y": 0.0}], "scale": [{"time": 0.0, "x": 1.0, "y": 1.0, "curve": "stepped"}, {"time": 2.0, "x": 1.0, "y": 1.0}]}, "line1_1": {"rotate": [{"time": 0.0, "angle": -0.5850143432617188, "curve": [0.25, 0.0, 0.75, 1.0]}, {"time": 1.0, "angle": 0.43441009521484375, "curve": [0.25, 0.0, 0.75, 1.0]}, {"time": 2.0, "angle": -0.5850143432617188}], "translate": [{"time": 0.0, "x": 0.0, "y": 0.0, "curve": "stepped"}, {"time": 2.0, "x": 0.0, "y": 0.0}], "scale": [{"time": 0.0, "x": 1.0, "y": 1.0, "curve": "stepped"}, {"time": 2.0, "x": 1.0, "y": 1.0}]}, "line1": {"rotate": [{"time": 0.0, "angle": 0.0, "curve": "stepped"}, {"time": 2.0, "angle": 0.0}], "translate": [{"time": 0.0, "x": 0.0, "y": 0.0, "curve": "stepped"}, {"time": 2.0, "x": 0.0, "y": 0.0}], "scale": [{"time": 0.0, "x": 1.0, "y": 1.0, "curve": "stepped"}, {"time": 2.0, "x": 1.0, "y": 1.0}]}, "line2": {"rotate": [{"time": 0.0, "angle": 0.0, "curve": "stepped"}, {"time": 2.0, "angle": 0.0}], "translate": [{"time": 0.0, "x": 0.0, "y": 0.0, "curve": "stepped"}, {"time": 2.0, "x": 0.0, "y": 0.0}], "scale": [{"time": 0.0, "x": 1.0, "y": 1.0, "curve": "stepped"}, {"time": 2.0, "x": 1.0, "y": 1.0}]}, "line3": {"rotate": [{"time": 0.0, "angle": 0.0, "curve": "stepped"}, {"time": 2.0, "angle": 0.0}], "translate": [{"time": 0.0, "x": 0.0, "y": 0.0, "curve": "stepped"}, {"time": 2.0, "x": 0.0, "y": 0.0}], "scale": [{"time": 0.0, "x": 1.0, "y": 1.0, "curve": "stepped"}, {"time": 2.0, "x": 1.0, "y": 1.0}]}, "ik_line3": {"rotate": [{"time": 0.0, "angle": 0.0, "curve": "stepped"}, {"time": 2.0, "angle": 0.0}], "translate": [{"time": 0.0, "x": 0.0, "y": 0.0, "curve": "stepped"}, {"time": 2.0, "x": 0.0, "y": 0.0}], "scale": [{"time": 0.0, "x": 1.0, "y": 1.0, "curve": "stepped"}, {"time": 2.0, "x": 1.0, "y": 1.0}]}, "line1_8": {"rotate": [{"time": 0.0, "angle": 0.0, "curve": "stepped"}, {"time": 2.0, "angle": 0.0}], "translate": [{"time": 0.0, "x": 0.0, "y": 0.0, "curve": "stepped"}, {"time": 2.0, "x": 0.0, "y": 0.0}], "scale": [{"time": 0.0, "x": 1.0, "y": 1.0, "curve": "stepped"}, {"time": 2.0, "x": 1.0, "y": 1.0}]}, "ik_line2": {"rotate": [{"time": 0.0, "angle": 0.0, "curve": "stepped"}, {"time": 2.0, "angle": 0.0}], "translate": [{"time": 0.0, "x": 0.0, "y": 0.0, "curve": "stepped"}, {"time": 2.0, "x": 0.0, "y": 0.0}], "scale": [{"time": 0.0, "x": 1.0, "y": 1.0, "curve": "stepped"}, {"time": 2.0, "x": 1.0, "y": 1.0}]}, "line1_5": {"rotate": [{"time": 0.0, "angle": 0.0, "curve": "stepped"}, {"time": 2.0, "angle": 0.0}], "translate": [{"time": 0.0, "x": 0.0, "y": 0.0, "curve": "stepped"}, {"time": 2.0, "x": 0.0, "y": 0.0}], "scale": [{"time": 0.0, "x": 1.0, "y": 1.0, "curve": "stepped"}, {"time": 2.0, "x": 1.0, "y": 1.0}]}, "ik_line1": {"rotate": [{"time": 0.0, "angle": 0.0, "curve": "stepped"}, {"time": 2.0, "angle": 0.0}], "translate": [{"time": 0.0, "x": 0.0, "y": 0.0, "curve": "stepped"}, {"time": 2.0, "x": 0.0, "y": 0.0}], "scale": [{"time": 0.0, "x": 1.0, "y": 1.0, "curve": "stepped"}, {"time": 2.0, "x": 1.0, "y": 1.0}]}, "line1_3": {"rotate": [{"time": 0.0, "angle": 0.0, "curve": "stepped"}, {"time": 2.0, "angle": 0.0}], "translate": [{"time": 0.0, "x": 0.0, "y": 0.0, "curve": "stepped"}, {"time": 2.0, "x": 0.0, "y": 0.0}], "scale": [{"time": 0.0, "x": 1.0, "y": 1.0, "curve": "stepped"}, {"time": 2.0, "x": 1.0, "y": 1.0}]}, "line1_6": {"rotate": [{"time": 0.0, "angle": 0.0, "curve": "stepped"}, {"time": 2.0, "angle": 0.0}], "translate": [{"time": 0.0, "x": 0.0, "y": 0.0, "curve": "stepped"}, {"time": 2.0, "x": 0.0, "y": 0.0}], "scale": [{"time": 0.0, "x": 1.0, "y": 1.0, "curve": "stepped"}, {"time": 2.0, "x": 1.0, "y": 1.0}]}, "line1_9": {"rotate": [{"time": 0.0, "angle": 0.0, "curve": "stepped"}, {"time": 2.0, "angle": 0.0}], "translate": [{"time": 0.0, "x": 0.0, "y": 0.0, "curve": "stepped"}, {"time": 2.0, "x": 0.0, "y": 0.0}], "scale": [{"time": 0.0, "x": 1.0, "y": 1.0, "curve": "stepped"}, {"time": 2.0, "x": 1.0, "y": 1.0}]}, "bone": {"rotate": [{"time": 0.0, "angle": -1.3968725204467773, "curve": [0.3203883469104767, 0.2857142984867096, 0.7572815418243408, 1.0]}, {"time": 0.800000011920929, "angle": -10.73714542388916, "curve": [0.25, 0.0, 0.75, 1.0]}, {"time": 1.7999999523162842, "angle": 0.0, "curve": [0.28409090638160706, 0.0, 0.625, 0.38461539149284363]}, {"time": 2.0, "angle": -1.3968725204467773}], "translate": [{"time": 0.0, "x": 0.0, "y": 0.0, "curve": "stepped"}, {"time": 2.0, "x": 0.0, "y": 0.0}], "scale": [{"time": 0.0, "x": 1.0, "y": 1.0, "curve": "stepped"}, {"time": 2.0, "x": 1.0, "y": 1.0}]}}, "ik": {}, "transform": {}, "draworder": [{"time": 0.0, "offsets": []}, {"time": 2.0, "offsets": []}], "deform": {"default": {"doll1_head": {"doll1_head": [{"time": 0.0, "curve": "stepped"}, {"time": 2.0}]}, "doll1_l_arm_up": {"doll1_l_arm_up": [{"time": 0.0, "curve": "stepped"}, {"time": 2.0}]}, "doll1_r_arm_up": {"doll1_r_arm_up": [{"time": 0.0, "curve": "stepped"}, {"time": 2.0}]}, "doll1_ribbon": {"doll1_ribbon": [{"time": 0.0, "curve": "stepped"}, {"time": 2.0}]}, "doll1_skirt1": {"doll1_skirt1": [{"time": 0.0, "curve": "stepped"}, {"time": 2.0}]}, "doll1_skirt2": {"doll1_skirt2": [{"time": 0.0, "curve": "stepped"}, {"time": 2.0}]}, "doll1_skirt3": {"doll1_skirt3": [{"time": 0.0, "curve": "stepped"}, {"time": 2.0}]}, "line1": {"line": [{"time": 0.0, "curve": "stepped"}, {"time": 2.0}]}, "line2": {"line": [{"time": 0.0, "curve": "stepped"}, {"time": 2.0}]}, "line3": {"line": [{"time": 0.0, "curve": "stepped"}, {"time": 2.0}]}}}}}}